[{"accessToken":"c70d118b0933131def4b48a044d66714","$exists":false,"$new":true,"lang":"ar","theme":"theme_paper","data":[],"ip_info":{},"requestesCount":1,"createdTime":1661218250957,"$index":0,"ip":"127.0.0.1","modifiedTime":1661220122575},{"accessToken":"8509397ae5b27d6a1f1ca3e73625be76","$exists":false,"$new":true,"lang":"en","theme":"theme_paper","data":[],"ip_info":{},"requestesCount":1,"createdTime":1661220138584,"$index":1,"ip":"127.0.0.1","modifiedTime":1661268513596},{"accessToken":"d32afb4cc875fa853b58e2bdde61c639","$exists":false,"$new":true,"lang":"en","theme":"theme_paper","data":[],"ip_info":{},"requestesCount":1,"createdTime":1661332847793,"$index":2,"ip":"127.0.0.1","modifiedTime":1661335090518}]